[
  {
    "id": 1772476933949,
    "type": "long-term",
    "title": "新学期电子注册",
    "target": "",
    "content": "请同学们尽快完成新学期的电子信息注册！\n网址：http://xgyth.ustc.edu.cn",
    "publishTime": "2026-03-02T18:42:13.950Z",
    "deadline": "2026-03-15T23:59",
    "images": [
      "images/新学期电子注册.jpg"
    ]
  },
  {
    "id": 1772546313783,
    "type": "long-term",
    "title": "领取教材",
    "target": "",
    "content": "1、如果有教材需要增减，请私聊syh说明!\n2、《数学分析B2》《大物实验》《大心》《中英文科技论文写作》《热学 张玉民》这几本书教材库缺少，没拿到的同学要么再等待几天、要么选择自行购买（向我说明不需要哪本书）",
    "publishTime": "2026-03-03T13:58:33.783Z",
    "deadline": "2026-03-06T18:00",
    "images": []
  },
  {
    "id": 1772546600257,
    "type": "long-term",
    "title": "团员大会准备",
    "target": "全体团员",
    "content": "定于2026.3.6晚上19:00于东区一教1102召开班会与团员大会。其中团员大会需要每位团员进行批评与自我批评，请提前准备，不做时长/字数要求，务实为主；同时会进行团员的民主评议，每位团员对支部其他团员进行评价，评议为优是申请优秀团员/团干的前置条件。",
    "publishTime": "2026-03-03T14:03:20.257Z",
    "deadline": "TBD",
    "isUrgent": true,
    "images": []
  }
]
